qfile/__init__.py
qfile/archiving.py
qfile/clipboard.py
qfile/dirs.py
qfile/file.py
qfile/modify.py
qfile/relocate.py
qfile-1.1.0.7.dist-info/METADATA
qfile-1.1.0.7.dist-info/WHEEL
qfile-1.1.0.7.dist-info/top_level.txt
qfile-1.1.0.7.dist-info/RECORD
