Metadata-Version: 2.1
Name: qfile
Version: 1.1.0.7
Summary: A python library for simplifying common file operations.
Home-page: https://github.com/xMGZx/qfile
Author: Zach K (mathgeniuszach)
Author-email: huntingmanzach@gmail.com
License: UNKNOWN
Platform: UNKNOWN
Classifier: Programming Language :: Python :: 3
